entryclient/__init__.py
entryclient/message_pb2.py
entryclient-2.3.2.dist-info/DESCRIPTION.rst
entryclient-2.3.2.dist-info/METADATA
entryclient-2.3.2.dist-info/RECORD
entryclient-2.3.2.dist-info/WHEEL
entryclient-2.3.2.dist-info/metadata.json
entryclient-2.3.2.dist-info/top_level.txt
