Metadata-Version: 2.0
Name: entryclient
Version: 2.3.2
Summary: UNKNOWN
Home-page: UNKNOWN
Author: EricPai <ericpai94@hotmail.com>
Author-email: UNKNOWN
License: UNKNOWN
Platform: UNKNOWN
Requires-Dist: protobuf (==3.0.0b3)
Requires-Dist: six (>=1.9.0)
Requires-Dist: websocket-client (==0.32.0)
